intake_gfs_ncar/__init__.py
intake_gfs_ncar/compare_gfs_sources.py
intake_gfs_ncar/gfs_catalog.yaml
intake_gfs_ncar/gfs_intake_driver.py
intake_gfs_ncar-0.4.12.dist-info/licenses/LICENSE
intake_gfs_ncar-0.4.12.dist-info/METADATA
intake_gfs_ncar-0.4.12.dist-info/WHEEL
intake_gfs_ncar-0.4.12.dist-info/entry_points.txt
intake_gfs_ncar-0.4.12.dist-info/top_level.txt
intake_gfs_ncar-0.4.12.dist-info/RECORD
