Metadata-Version: 2.4
Name: intake-gfs-ncar
Version: 0.4.12
Summary: Intake driver for NCAR GFS forecast data
Author-email: Oceanum Developers <developers@oceanum.science>
License-Expression: MIT
Project-URL: Homepage, https://github.com/oceanum/intake-gfs-ncar
Project-URL: Bug_Tracker, https://github.com/oceanum/intake-gfs-ncar/issues
Project-URL: Documentation, https://github.com/oceanum/intake-gfs-ncar#readme
Project-URL: Changelog, https://github.com/oceanum/intake-gfs-ncar/blob/main/CHANGELOG.md
Classifier: Development Status :: 4 - Beta
Classifier: Intended Audience :: Science/Research
Classifier: Programming Language :: Python :: 3
Classifier: Programming Language :: Python :: 3.9
Classifier: Programming Language :: Python :: 3.10
Classifier: Programming Language :: Python :: 3.11
Classifier: Topic :: Scientific/Engineering
Classifier: Topic :: Scientific/Engineering :: Atmospheric Science
Requires-Python: >=3.9
License-File: LICENSE
Requires-Dist: intake>=0.6.5
Requires-Dist: xarray>=2022.3.0
Requires-Dist: cfgrib>=0.9.10
Requires-Dist: fsspec>=2021.10.0
Requires-Dist: aiohttp>=3.8.0
Requires-Dist: dask>=2022.2.0
Requires-Dist: pandas>=1.3.0
Requires-Dist: python-dateutil>=2.8.2
Requires-Dist: netCDF4>=1.6.0
Requires-Dist: cftime>=1.6.0
Provides-Extra: plotting
Requires-Dist: matplotlib>=3.5.0; extra == "plotting"
Requires-Dist: cartopy>=0.21.0; extra == "plotting"
Provides-Extra: test
Requires-Dist: pytest>=7.0.0; extra == "test"
Requires-Dist: pytest-cov>=4.0.0; extra == "test"
Provides-Extra: docs
Requires-Dist: sphinx>=5.0.0; extra == "docs"
Requires-Dist: sphinx-rtd-theme>=1.2.0; extra == "docs"
Requires-Dist: nbsphinx>=0.8.12; extra == "docs"
Provides-Extra: dev
Requires-Dist: black>=23.0.0; extra == "dev"
Requires-Dist: isort>=5.12.0; extra == "dev"
Requires-Dist: mypy>=1.0.0; extra == "dev"
Requires-Dist: flake8>=6.0.0; extra == "dev"
Requires-Dist: build>=0.10.0; extra == "dev"
Requires-Dist: twine>=4.0.0; extra == "dev"
Requires-Dist: pytest>=7.0.0; extra == "dev"
Requires-Dist: pytest-cov>=4.0.0; extra == "dev"
Provides-Extra: all
Requires-Dist: intake-gfs-ncar[dev,docs,plotting,test]; extra == "all"
Dynamic: license-file
